README.md
setup.py
nicok_mytest.egg-info/PKG-INFO
nicok_mytest.egg-info/SOURCES.txt
nicok_mytest.egg-info/dependency_links.txt
nicok_mytest.egg-info/requires.txt
nicok_mytest.egg-info/top_level.txt
pyfi/__init__.py
pyfi/modul1.py
pyfi/modul2.py