Metadata-Version: 2.1
Name: nicok-mytest
Version: 0.0.6
Summary: Demonstrating how to use PyPI
Home-page: UNKNOWN
Author: Nico
Author-email: pypi@nk7.de
License: UNKNOWN
Keywords: python,code
Platform: UNKNOWN
Classifier: Development Status :: 1 - Planning
Classifier: Intended Audience :: Developers
Classifier: Programming Language :: Python :: 3
Classifier: Operating System :: Microsoft :: Windows
